setup.cfg
setup.py
earning/__init__.py
earning.egg-info/PKG-INFO
earning.egg-info/SOURCES.txt
earning.egg-info/dependency_links.txt
earning.egg-info/top_level.txt