Metadata-Version: 1.1
Name: earning
Version: 1.0.0
Summary: This module is used to scarp earning information from both yahoo and nasdaq
Home-page: https://github.com/ShallweXiaowei/earning
Author: Xiaowei Yan
Author-email: shufeyxw@gmail.com
License: MIT
Download-URL: https://github.com/ShallweXiaowei/earning/archive/1.0.tar.gz
Platform: UNKNOWN
